{
  "languages": {
    "ar": "арапски",
    "bs": "босански",
    "ckb": "курдски (сорани)",
    "de": "немачки",
    "en": "енглески",
    "es": "шпански",
    "fa": "фарси",
    "fr": "француски",
    "ka": "грузијски",
    "ku": "курдски",
    "mk": "македонски",
    "ps": "пашто",
    "ru": "руски",
    "so": "сомалијски",
    "sq": "Албанац",
    "sr": "српски",
    "ti": "Тигриња",
    "tr": "турски",
    "uk": "украјински",
    "vi": "вијетнамски",
    "ur": "Урду",
    "findTranslation": "Превод доступан на српском језику",
    "machineTranslation": "Nažalost, prevedeno je samo pomoću veštačke inteligencije. Molimo te da nam pomogneš da poboljšamo informacije i pošalješ nam mejl" 
  }
}
